ml_adapter/base/__init__.py
ml_adapter/base/adapter.py
ml_adapter/base/py.typed
ml_adapter/base/assets/__init__.py
ml_adapter/base/assets/_err.py
ml_adapter/base/assets/base.py
ml_adapter/base/assets/cached.py
ml_adapter/base/assets/default.plug.json
ml_adapter/base/assets/default.v1.plug.json
ml_adapter/base/assets/default.v1.webscript.json
ml_adapter/base/assets/default.v2.plug.json
ml_adapter/base/assets/default.webscript.json
ml_adapter/base/assets/json.py
ml_adapter/base/assets/manifest.py
ml_adapter/base/assets/mixin.py
ml_adapter/base/assets/node.py
ml_adapter/base/assets/openapi.py
ml_adapter/base/assets/python.py
ml_adapter/base/assets/python_ml.py
ml_adapter/base/assets/root.py
ml_adapter/base/assets/script.py
ml_adapter/base/marshall/__init__.py
ml_adapter/base/marshall/base.py
ml_adapter/base/marshall/v1/__init__.py
ml_adapter/base/marshall/v1/base.py
ml_adapter/base/marshall/v1/list.py
ml_adapter/base/model/__init__.py
ml_adapter/base/model/access.py
ml_adapter/base/model/base.py
ml_adapter/base/model/dill.py
ml_adapter/base/model/joblib.py
ml_adapter/base/model/serialize.py
waylay_ml_adapter_base-0.1.1.dist-info/licenses/LICENCE.txt
waylay_ml_adapter_base-0.1.1.dist-info/METADATA
waylay_ml_adapter_base-0.1.1.dist-info/WHEEL
waylay_ml_adapter_base-0.1.1.dist-info/top_level.txt
waylay_ml_adapter_base-0.1.1.dist-info/RECORD
