Metadata-Version: 2.4
Name: waylay-ml-adapter-base
Version: 0.1.1
Summary: ml-adapter base classes.
Author-email: Waylay <info@waylay.io>
Requires-Python: >=3.11
License-File: LICENCE.txt
Requires-Dist: waylay-ml-adapter-api
Requires-Dist: openapi-spec-validator
Provides-Extra: dill
Requires-Dist: dill; extra == "dill"
Provides-Extra: joblib
Requires-Dist: joblib; extra == "joblib"
Provides-Extra: starlette
Requires-Dist: httpx; extra == "starlette"
Requires-Dist: starlette; extra == "starlette"
Provides-Extra: dev
Requires-Dist: waylay-ml-adapter-devtools; extra == "dev"
Requires-Dist: joblib; extra == "dev"
Requires-Dist: dill; extra == "dev"
Requires-Dist: httpx; extra == "dev"
Requires-Dist: starlette; extra == "dev"
Dynamic: license-file
